MIPS_32/MIPS_32.srcs/sources_1/new/pipes_MIPSS32.v
`timescale 1s / 1ms

module pipes_MIPSS32 (clk1, clk2);

// Two-phase clock
input clk1, clk2;

reg [31:0] PC, IF_ID_IR, IF_ID_NPC;
reg [31:0] ID_EX_IR, ID_EX_NPC, ID_EX_A, ID_EX_B, ID_EX_Imm;
reg [2:0]  ID_EX_type, EX_MEM_type, MEM_WB_type;
reg [31:0] EX_MEM_IR, EX_MEM_ALUOut, EX_MEM_B;
reg        EX_MEM_cond;
reg [31:0] MEM_WB_IR, MEM_WB_ALUOut, MEM_WB_LMD;

reg [31:0] Reg [0:31];     // Register bank (32 x 32)
reg [31:0] Mem [0:1023];   // 1024 x 32 memory

parameter ADD=6'b000000, SUB=6'b000001, AND=6'b000010, OR=6'b000011,
          SLT=6'b000100, MUL=6'b000101, HLT=6'b111111, LW=6'b100000,
          SW=6'b100001, ADDI=6'b001010, SUBI=6'b001011, SLTI=6'b001100,
          BNEQZ=6'b001101, BEQZ=6'b001110;
          
parameter RR_ALU=3'b000, RM_ALU=3'b001, LOAD=3'b010, STORE=3'b011,
          BRANCH=3'b100, HALT=3'b101;

reg HALTED;           // Set after HLT instruction is completed (in WB stage)

reg TAKEN_BRANCH;     // Required to disable instructions after branch

always @ (posedge clk1)        // IF Stage
  if (HALTED == 0)
  begin
    if (((EX_MEM_IR[31:26] == BEQZ) && (EX_MEM_cond == 1)) ||
        ((EX_MEM_IR[31:26] == BNEQZ) && (EX_MEM_cond == 0)))
    begin
      IF_ID_IR    <= #2 Mem[EX_MEM_ALUOut];
      TAKEN_BRANCH <= #2 1'b1;
      IF_ID_NPC   <= #2 EX_MEM_ALUOut + 1;
      PC          <= #2 EX_MEM_ALUOut + 1;
    end
    else
    begin
      IF_ID_IR   <= #2 Mem[PC];
      IF_ID_NPC  <= #2 PC + 1;
      PC         <= #2 PC + 1;
    end
  end

always @ (posedge clk2)         // ID Stage
  if (HALTED == 0)
  begin
    if (IF_ID_IR[25:21] == 5'b00000)  ID_EX_A <= 0;
    else ID_EX_A <= #2 Reg[IF_ID_IR[25:21]];   // "rs"

    if (IF_ID_IR[20:16] == 5'b00000)  ID_EX_B <= 0;
    else ID_EX_B <= #2 Reg[IF_ID_IR[20:16]];   // "rt"

    ID_EX_NPC  <= #2 IF_ID_NPC;
    ID_EX_IR   <= #2 IF_ID_IR;
    ID_EX_Imm  <= #2 {{16{IF_ID_IR[15]}}, {IF_ID_IR[15:0]}};
  

    case (IF_ID_IR[31:26])
      ADD, SUB, AND, OR, SLT, MUL:   ID_EX_type <= #2 RR_ALU;
      ADDI, SUBI, SLTI:              ID_EX_type <= #2 RM_ALU;
      LW:                            ID_EX_type <= #2 LOAD;
      SW:                            ID_EX_type <= #2 STORE;
      BNEQZ, BEQZ:                   ID_EX_type <= #2 BRANCH;
      HLT:                           ID_EX_type <= #2 HALT;
      default:                       ID_EX_type <= #2 HALT;     // Invalid opcode
    endcase
  end

always @ (posedge clk1)        // EX Stage
  if (HALTED == 0)
  begin
    EX_MEM_type <= #2 ID_EX_type;
    EX_MEM_IR   <= #2 ID_EX_IR;
    TAKEN_BRANCH <= #2 0;

    case (ID_EX_type)
      RR_ALU: begin
        case (ID_EX_IR[31:26])      // "opcode"
          ADD:    EX_MEM_ALUOut <= #2 ID_EX_A + ID_EX_B;
          SUB:    EX_MEM_ALUOut <= #2 ID_EX_A - ID_EX_B;
          AND:    EX_MEM_ALUOut <= #2 ID_EX_A & ID_EX_B;
          OR:     EX_MEM_ALUOut <= #2 ID_EX_A | ID_EX_B;
          SLT:    EX_MEM_ALUOut <= #2 ID_EX_A < ID_EX_B;
          MUL:    EX_MEM_ALUOut <= #2 ID_EX_A * ID_EX_B;
          default: EX_MEM_ALUOut <= #2 32'hxxxxxxxx;
        endcase
             end
     RM_ALU: begin
  case (ID_EX_IR[31:26])        // "opcode"
    ADDI:   EX_MEM_ALUOut <= #2 ID_EX_A + ID_EX_Imm;
    SUBI:   EX_MEM_ALUOut <= #2 ID_EX_A - ID_EX_Imm;
    SLTI:   EX_MEM_ALUOut <= #2 ID_EX_A < ID_EX_Imm;
    default: EX_MEM_ALUOut <= #2 32'hxxxxxxxx;
  endcase
end
               LOAD, STORE:
                begin
                    EX_MEM_ALUOut   <= #2 ID_EX_A + ID_EX_Imm;
                    EX_MEM_B        <= #2 ID_EX_B;
                end

            BRANCH: begin
                    EX_MEM_ALUOut   <= #2 ID_EX_NPC + ID_EX_Imm;
                    EX_MEM_cond     <= #2 (ID_EX_A == 0);
                end
        endcase
    end

always @(posedge clk2)                         // MEM Stage
    if (HALTED == 0)
    begin
        MEM_WB_type    <= EX_MEM_type;
        MEM_WB_IR      <= #2 EX_MEM_IR;

        case (EX_MEM_type)
            RR_ALU, RM_ALU:
                MEM_WB_ALUOut <= #2 EX_MEM_ALUOut;

            LOAD:      MEM_WB_LMD <= #2 Mem[EX_MEM_ALUOut];

            STORE:     if (TAKEN_BRANCH == 0)    // Disable write
                           Mem[EX_MEM_ALUOut] <= #2 EX_MEM_B;
        endcase
    end

always @ (posedge clk1)                     // WB Stage
    begin
        if (TAKEN_BRANCH == 0)             // Disable write if branch taken
            case (MEM_WB_type)
                RR_ALU:   Reg[MEM_WB_IR[15:11]] <= #2 MEM_WB_ALUOut;   // "rd"
                RM_ALU:   Reg[MEM_WB_IR[20:16]] <= #2 MEM_WB_ALUOut;   // "rt"
                LOAD:     Reg[MEM_WB_IR[20:16]] <= #2 MEM_WB_LMD;      // "rt"
                HALT:     HALTED <= #2 1'b1;
            endcase
    end

endmodule

MIPS_32/MIPS_32.srcs/sim_1/new/test2_mips32.v
`timescale 1s / 1ms

module test2_mips32;

 reg clk1, clk2;
 integer k;
 
 pipes_MIPSS32 mips(clk1,clk2);
 
 initial
   begin
     clk1=0; clk2=0;
     repeat (50)         //generating 2 phase clock
       begin
         #5 clk1=1; #5 clk1=0;
         #5 clk2=1; #5 clk2=0;
       end
   end
   
 initial 
   begin
     for(k=0;k<31;k=k+1)
       mips.Reg[k]=k;
       
       mips.Mem[0] = 32'h28010078; //ADDI R1,R0,120
       mips.Mem[1] = 32'h0c631800; //OR   R3,R3,R3 -- Dummy Instruction
       mips.Mem[2] = 32'h20220000; //LW   R2,0(R1)
       mips.Mem[3] = 32'h0c631800; //OR   R3,R3,R3 -- Dummy Instruction
       mips.Mem[4] = 32'h2842002d; //ADDI R2,R2,45
       mips.Mem[5] = 32'h0c631800; //OR   R3,R3,R3 -- Dummy Instruction
       mips.Mem[6] = 32'h24220001; //SW   R2,1(R1)
       mips.Mem[7] = 32'hfc000000; //HLT
       
       mips.Mem[120] = 85; 
       
       mips.PC = 0;
          mips.HALTED = 0; 
          mips.TAKEN_BRANCH = 0;
          
          #500 $display("Mem[120]: %4d \nMem[121]: %4d", mips.Mem[120], mips.Mem[121]);
          
    end
    
    initial 
   begin
     $dumpfile ("mips.vcd");
     $dumpvars (0,test2_mips32);
    
     #600 $finish;
   end
endmodule

MIPS_32/MIPS_32.sim/sim_2/behav/xsim/mips.vcd
$date
   Sat Jul  5 16:12:51 2025
$end
$version
  2018.3
$end
$timescale
  1ps
$end
$scope module test2_mips32 $end
$var reg 1 ! clk1 $end
$var reg 1 " clk2 $end
$var integer 32 # k $end
$scope module mips $end
$var wire 1 $ clk1 $end
$var wire 1 % clk2 $end
$var reg 32 & PC [31:0] $end
$var reg 32 ' IF_ID_IR [31:0] $end
$var reg 32 ( IF_ID_NPC [31:0] $end
$var reg 32 ) ID_EX_IR [31:0] $end
$var reg 32 * ID_EX_NPC [31:0] $end
$var reg 32 + ID_EX_A [31:0] $end
$var reg 32 , ID_EX_B [31:0] $end
$var reg 32 - ID_EX_Imm [31:0] $end
$var reg 3 . ID_EX_type [2:0] $end
$var reg 3 / EX_MEM_type [2:0] $end
$var reg 3 0 MEM_WB_type [2:0] $end
$var reg 32 1 EX_MEM_IR [31:0] $end
$var reg 32 2 EX_MEM_ALUOut [31:0] $end
$var reg 32 3 EX_MEM_B [31:0] $end
$var reg 1 4 EX_MEM_cond $end
$var reg 32 5 MEM_WB_IR [31:0] $end
$var reg 32 6 MEM_WB_ALUOut [31:0] $end
$var reg 32 7 MEM_WB_LMD [31:0] $end
$var reg 1 8 HALTED $end
$var reg 1 9 TAKEN_BRANCH $end
$var parameter 6 : ADD [5:0] $end
$var parameter 6 ; SUB [5:0] $end
$var parameter 6 < AND [5:0] $end
$var parameter 6 = OR [5:0] $end
$var parameter 6 > SLT [5:0] $end
$var parameter 6 ? MUL [5:0] $end
$var parameter 6 @ HLT [5:0] $end
$var parameter 6 A LW [5:0] $end
$var parameter 6 B SW [5:0] $end
$var parameter 6 C ADDI [5:0] $end
$var parameter 6 D SUBI [5:0] $end
$var parameter 6 E SLTI [5:0] $end
$var parameter 6 F BNEQZ [5:0] $end
$var parameter 6 G BEQZ [5:0] $end
$var parameter 3 H RR_ALU [2:0] $end
$var parameter 3 I RM_ALU [2:0] $end
$var parameter 3 J LOAD [2:0] $end
$var parameter 3 K STORE [2:0] $end
$var parameter 3 L BRANCH [2:0] $end
$var parameter 3 M HALT [2:0] $end
$upscope $end
$upscope $end
$enddefinitions $end
#0
$dumpvars
0!
0"
b11111 #
0$
0%
b0 &
bx '
bx (
bx )
bx *
bx +
bx ,
bx -
bx .
bx /
bx 0
bx 1
bx 2
bx 3
x4
bx 5
bx 6
bx 7
08
09
b0 :
b1 ;
b10 <
b11 =
b100 >
b101 ?
b111111 @
b100000 A
b100001 B
b1010 C
b1011 D
b1100 E
b1101 F
b1110 G
b0 H
b1 I
b10 J
b11 K
b100 L
b101 M
$end
#5
1!
1$
#7
b1 &
b101000000000010000000001111000 '
b1 (
#10
0!
0$
#15
1"
1%
b0 +
#17
b101000000000010000000001111000 )
b1 *
b1 ,
b1111000 -
b1 .
#20
0"
0%
#25
1!
1$
#27
b10 &
b1100011000110001100000000000 '
b10 (
b1 /
b101000000000010000000001111000 1
b1111000 2
#30
0!
0$
#35
1"
1%
b1 0
#37
b1100011000110001100000000000 )
b10 *
b11 +
b11 ,
b1100000000000 -
b0 .
b101000000000010000000001111000 5
b1111000 6
#40
0"
0%
#45
1!
1$
#47
b11 &
b100000001000100000000000000000 '
b11 (
b0 /
b1100011000110001100000000000 1
b11 2
#50
0!
0$
#55
1"
1%
b0 0
#57
b100000001000100000000000000000 )
b11 *
b1111000 +
b10 ,
b0 -
b101 .
b1100011000110001100000000000 5
b11 6
#60
0"
0%
#65
1!
1$
#67
b100 &
b1100011000110001100000000000 '
b100 (
b101 /
b100000001000100000000000000000 1
#70
0!
0$
#75
1"
1%
b101 0
#77
b1100011000110001100000000000 )
b100 *
b11 +
b11 ,
b1100000000000 -
b0 .
b100000001000100000000000000000 5
#80
0"
0%
#85
1!
1$
#87
b101 &
b101000010000100000000000101101 '
b101 (
b0 /
b1100011000110001100000000000 1
18
